pyofc2
